xml_browser.py
xml_browser-0.99.dev2.dist-info/DESCRIPTION.rst
xml_browser-0.99.dev2.dist-info/METADATA
xml_browser-0.99.dev2.dist-info/RECORD
xml_browser-0.99.dev2.dist-info/WHEEL
xml_browser-0.99.dev2.dist-info/entry_points.txt
xml_browser-0.99.dev2.dist-info/metadata.json
xml_browser-0.99.dev2.dist-info/top_level.txt
