Metadata-Version: 2.0
Name: xml-browser
Version: 0.99.dev2
Summary: Edit XML documents as a directory structure
Home-page: https://github.com/rasguanabana/xml_browser
Author: Adrian Włosiak
Author-email: adwlosiakh@gmail.com
License: MIT
Keywords: xml editing
Platform: UNKNOWN
Classifier: Development Status :: 3 - Alpha
Classifier: Intended Audience :: Developers
Classifier: License :: OSI Approved :: MIT License
Classifier: Operating System :: OS Independent
Classifier: Programming Language :: Python :: 2
Classifier: Programming Language :: Python :: 3
